file_transfer/__init__.py
file_transfer/api.py
file_transfer/application.py
file_transfer/get_event.py
file_transfer/handler.py
file_transfer/sample_events.py
file_transfer/controllers/base_controller.py
file_transfer/controllers/downloader_controller.py
file_transfer/controllers/uploader_controller.py
file_transfer/factories/base_factory.py
file_transfer/factories/factory.py
file_transfer/infra/compresser/zip_compresser.py
file_transfer/infra/local_downloader/local_downloader.py
file_transfer/infra/local_file_saver/local_file_saver.py
file_transfer/infra/pure_file_saver/pure_file_saver.py
file_transfer/infra/s3_downloader/s3_downloader.py
file_transfer/infra/s3_file_saver/s3_file_saver.py
file_transfer/models/image.py
file_transfer/models/request.py
file_transfer/models/response.py
file_transfer/services/base_service.py
file_transfer/services/downloader_service.py
file_transfer/services/uploader_service.py
file_transfer/utils/file.py
file_transfer/utils/helpers.py
file_transfer/utils/html.py
file_transfer/utils/json.py
file_transfer/utils/lambda_helpers.py
file_transfer/utils/markdown.py
file_transfer/utils/string_utils.py
file_transfer/utils/text.py
file_transfer/utils/time.py
file_transfer/utils/url.py
video_bot_file_transfer-0.0.18.dist-info/LICENSE
video_bot_file_transfer-0.0.18.dist-info/METADATA
video_bot_file_transfer-0.0.18.dist-info/WHEEL
video_bot_file_transfer-0.0.18.dist-info/top_level.txt
video_bot_file_transfer-0.0.18.dist-info/RECORD
