Metadata-Version: 2.1
Name: video-bot-file-transfer
Version: 0.0.18
Summary: File Transfer module
Author-email: Bruno de Paula <bruno.bert.jj@gmail.com>
License: MIT License
Project-URL: Homepage, https://github.com/bruno-bert/microservice-file-transfer
Keywords: file,transfer,s3
Classifier: Programming Language :: Python :: 3
Classifier: License :: OSI Approved :: MIT License
Classifier: Operating System :: OS Independent
Requires-Python: >=3.7
License-File: LICENSE
Requires-Dist: altgraph (==0.17.3)
Requires-Dist: aniso8601 (==9.0.1)
Requires-Dist: bleach (==5.0.1)
Requires-Dist: boto3 (==1.24.89)
Requires-Dist: botocore (==1.27.89)
Requires-Dist: build (==0.8.0)
Requires-Dist: certifi (==2022.9.24)
Requires-Dist: cffi (==1.15.1)
Requires-Dist: charset-normalizer (==2.1.1)
Requires-Dist: click (==8.1.3)
Requires-Dist: commonmark (==0.9.1)
Requires-Dist: cryptography (==38.0.1)
Requires-Dist: docutils (==0.19)
Requires-Dist: Flask (==2.2.2)
Requires-Dist: Flask-RESTful (==0.3.9)
Requires-Dist: idna (==3.4)
Requires-Dist: importlib-metadata (==5.0.0)
Requires-Dist: itsdangerous (==2.1.2)
Requires-Dist: jaraco.classes (==3.2.3)
Requires-Dist: jeepney (==0.8.0)
Requires-Dist: Jinja2 (==3.1.2)
Requires-Dist: jmespath (==1.0.1)
Requires-Dist: keyring (==23.9.3)
Requires-Dist: MarkupSafe (==2.1.1)
Requires-Dist: more-itertools (==8.14.0)
Requires-Dist: packaging (==21.3)
Requires-Dist: pep517 (==0.13.0)
Requires-Dist: pkginfo (==1.8.3)
Requires-Dist: pycparser (==2.21)
Requires-Dist: Pygments (==2.13.0)
Requires-Dist: pyparsing (==3.0.9)
Requires-Dist: python-dateutil (==2.8.2)
Requires-Dist: python-dotenv (==0.21.0)
Requires-Dist: pytz (==2022.4)
Requires-Dist: readme-renderer (==37.2)
Requires-Dist: requests (==2.28.1)
Requires-Dist: requests-toolbelt (==0.10.0)
Requires-Dist: rfc3986 (==2.0.0)
Requires-Dist: rich (==12.6.0)
Requires-Dist: s3transfer (==0.6.0)
Requires-Dist: SecretStorage (==3.3.3)
Requires-Dist: six (==1.16.0)
Requires-Dist: tomli (==2.0.1)
Requires-Dist: typing-extensions (==4.4.0)
Requires-Dist: urllib3 (==1.26.12)
Requires-Dist: webencodings (==0.5.1)
Requires-Dist: Werkzeug (==2.2.2)
Requires-Dist: zipp (==3.9.0)
